Metadata-Version: 1.0
Name: django-orphaned
Version: 0.1
Summary: delete all orphaned files from your models
Home-page: https://github.com/ledil/django-orphaned
Author: Leonardo Di Lella
Author-email: leonardo.dilella@mobileapart.com
License: MIT
Platform: UNKNOWN
Classifier: Development Status :: 3 - Alpha
Classifier: Environment :: Web Environment
Classifier: Framework :: Django
Classifier: Intended Audience :: Developers
Classifier: License :: OSI Approved :: MIT License
Classifier: Natural Language :: English
Classifier: Operating System :: POSIX :: Linux
Classifier: Programming Language :: Python
Classifier: Topic :: System :: Installation/Setup
